simple_drive/__init__.py
simple_drive/auth.py
simple_drive/constants.py
simple_drive/main.py
simple_drive/drive/__init__.py
simple_drive/drive/about.py
simple_drive/drive/comments.py
simple_drive/drive/files.py
simple_drive/drive/permissions.py
simple_drive/drive/replies.py
simple_drive/drive/revisions.py
simple_drive-2.0.9.dist-info/LICENSE
simple_drive-2.0.9.dist-info/METADATA
simple_drive-2.0.9.dist-info/WHEEL
simple_drive-2.0.9.dist-info/top_level.txt
simple_drive-2.0.9.dist-info/RECORD
