Metadata-Version: 2.1
Name: simple-drive
Version: 2.0.9
Summary: Use Google Drive API in the simplest way
Home-page: https://github.com/tranngocminhhieu/simple-drive
Author: Tran Ngoc Minh Hieu
Author-email: tnmhieu@gmail.com
License-File: LICENSE
Requires-Dist: colorama
Requires-Dist: pydrive2
Requires-Dist: google-api-python-client
Requires-Dist: oauth2client
